{
  "data": {
    "code_purpose": "model",
    "confidence": 0.95,
    "reasoning": "This is a Data Transfer Object (DTO) class based on multiple indicators:\n\n1. **File Path**: Located in `account-api/src/main/java/com/zixin/accountapi/dto/` - the `dto` package explicitly indicates this is a Data Transfer Object.\n\n2. **File Name**: `DeleteUserRequest.java` - the naming convention with \"Request\" suffix indicates this is a request model/DTO used to transfer data for a delete user operation.\n\n3. **Code Structure**: \n   - Simple POJO class with only a single field `userId` of type `Long[]`\n   - Uses Lombok's `@Data` annotation to auto-generate getters, setters, equals, hashCode, and toString methods\n   - No business logic, just data container\n\n4. **Purpose**: This class serves as a data model/DTO for carrying user deletion request parameters from client to server in an API context. It defines the structure of data expected when making a delete user request.\n\n5. **Characteristics**: Pure data structure with no behavior, typical of DTOs used in API request/response patterns."
  },
  "timestamp": 1770880433,
  "prompt_hash": "7e223ba75b16398a4407d3611258fa79",
  "token_usage": {
    "input_tokens": 247,
    "output_tokens": 318,
    "total_tokens": 565
  },
  "model_name": null
}